ogboost/__init__.py
ogboost/data.py
ogboost/main.py
ogboost/utils.py
ogboost/optional/__init__.py
ogboost/optional/parametric.py
ogboost/tests/test_concordance.py
ogboost/tests/test_cv_stratification.py
ogboost/tests/test_data.py
ogboost/tests/test_generate_heterogeneous_learners.py
ogboost/tests/test_gradient_boosting_ordinal.py
ogboost/tests/test_gradient_boosting_ordinal_extra.py
ogboost/tests/test_linear.py
ogboost/tests/test_linkfunctions.py
ogboost-0.8.1.dist-info/licenses/LICENSE
ogboost-0.8.1.dist-info/METADATA
ogboost-0.8.1.dist-info/WHEEL
ogboost-0.8.1.dist-info/top_level.txt
ogboost-0.8.1.dist-info/RECORD
