Metadata-Version: 2.4
Name: ogboost
Version: 0.8.1
Summary: Ordinal Gradient Boosting
Author-email: "Alireza S. Mahani, Mansour T.A. Sharabiani" <alireza.s.mahani@gmail.com>
License: MIT License
Keywords: ordinal regression,gradient boosting,machine learning,scikit-learn
License-File: LICENSE
Requires-Dist: numpy
Requires-Dist: pandas
Requires-Dist: scikit-learn
Requires-Dist: scipy
Requires-Dist: pydantic
Requires-Dist: pytest
Requires-Dist: matplotlib
Provides-Extra: param
Requires-Dist: statsmodels; extra == "param"
Dynamic: license-file
